finomaly/__init__.py
finomaly-0.1.5.dist-info/licenses/LICENSE
finomaly-0.1.5.dist-info/METADATA
finomaly-0.1.5.dist-info/WHEEL
finomaly-0.1.5.dist-info/top_level.txt
finomaly-0.1.5.dist-info/RECORD
