Metadata-Version: 2.4
Name: finomaly
Version: 0.1.5
Summary: A rule-based and machine learning-based anomaly detection library for financial transactions.
Author: Barisaksel
Project-URL: Source, https://github.com/Barisaksel/finomaly
Project-URL: PyPI, https://pypi.org/project/finomaly/
Keywords: anomaly detection,financial,machine learning,rule-based,fraud,outlier,python,data science,fintech,unsupervised learning
Classifier: Development Status :: 4 - Beta
Classifier: Intended Audience :: Developers
Classifier: Intended Audience :: Financial and Insurance Industry
Classifier: Topic :: Software Development :: Libraries :: Python Modules
Classifier: Topic :: Security
Classifier: Topic :: Scientific/Engineering :: Artificial Intelligence
Classifier: License :: OSI Approved :: MIT License
Classifier: Programming Language :: Python :: 3
Classifier: Programming Language :: Python :: 3.8
Classifier: Programming Language :: Python :: 3.9
Classifier: Programming Language :: Python :: 3.10
Classifier: Programming Language :: Python :: 3.11
Classifier: Operating System :: OS Independent
Requires-Python: >=3.8
License-File: LICENSE
Requires-Dist: scikit-learn
Requires-Dist: numpy
Requires-Dist: fpdf
Requires-Dist: matplotlib
Requires-Dist: seaborn
Requires-Dist: pandas
Requires-Dist: xgboost
Dynamic: author
Dynamic: classifier
Dynamic: description
Dynamic: description-content-type
Dynamic: keywords
Dynamic: license-file
Dynamic: project-url
Dynamic: requires-dist
Dynamic: requires-python
Dynamic: summary
